vroid/__init__.py
vroid/client.py
vroid/domain/__init__.py
vroid/domain/character.py
vroid/domain/character_model_verison.py
vroid/domain/image.py
vroid/domain/user.py
vroid/exception.py
vroid/oauth.py
vroid/parameter.py
vroid/request.py
vroid/route.py
vroid-0.1.1.dist-info/LICENSE
vroid-0.1.1.dist-info/METADATA
vroid-0.1.1.dist-info/WHEEL
vroid-0.1.1.dist-info/RECORD
